pneumonia_model_package/.DS_Store
pneumonia_model_package/VERSION
pneumonia_model_package/__init__.py
pneumonia_model_package/config/.DS_Store
pneumonia_model_package/config/__init__.py
pneumonia_model_package/config/core.py
pneumonia_model_package/config.yml
pneumonia_model_package/data_processing/.DS_Store
pneumonia_model_package/data_processing/__init__.py
pneumonia_model_package/data_processing/data_manager.py
pneumonia_model_package/data_processing/dataset_preprocessor.py
pneumonia_model_package/datasets/.DS_Store
pneumonia_model_package/datasets/__init__.py
pneumonia_model_package/datasets/pneumonia-data/.DS_Store
pneumonia_model_package/datasets/pneumonia-data/val/NORMAL2-IM-1427-0001.jpeg
pneumonia_model_package/datasets/pneumonia-data/val/NORMAL2-IM-1430-0001.jpeg
pneumonia_model_package/datasets/pneumonia-data/val/NORMAL2-IM-1431-0001.jpeg
pneumonia_model_package/datasets/pneumonia-data/val/NORMAL2-IM-1436-0001.jpeg
pneumonia_model_package/datasets/pneumonia-data/val/NORMAL2-IM-1437-0001.jpeg
pneumonia_model_package/datasets/pneumonia-data/val/NORMAL2-IM-1438-0001.jpeg
pneumonia_model_package/datasets/pneumonia-data/val/NORMAL2-IM-1440-0001.jpeg
pneumonia_model_package/datasets/pneumonia-data/val/NORMAL2-IM-1442-0001.jpeg
pneumonia_model_package/datasets/pneumonia-data/val/person1946_bacteria_4874.jpeg
pneumonia_model_package/datasets/pneumonia-data/val/person1946_bacteria_4875.jpeg
pneumonia_model_package/datasets/pneumonia-data/val/person1947_bacteria_4876.jpeg
pneumonia_model_package/datasets/pneumonia-data/val/person1949_bacteria_4880.jpeg
pneumonia_model_package/datasets/pneumonia-data/val/person1950_bacteria_4881.jpeg
pneumonia_model_package/datasets/pneumonia-data/val/person1951_bacteria_4882.jpeg
pneumonia_model_package/datasets/pneumonia-data/val/person1952_bacteria_4883.jpeg
pneumonia_model_package/datasets/pneumonia-data/val/person1954_bacteria_4886.jpeg
pneumonia_model_package/model.py
pneumonia_model_package/predict.py
pneumonia_model_package-0.3.0.dist-info/METADATA
pneumonia_model_package-0.3.0.dist-info/WHEEL
pneumonia_model_package-0.3.0.dist-info/RECORD
